<annotation>
	<folder>Images with Litter</folder>
	<filename>bautista_y151.jpg</filename>
	<path>C:\Users\Francis\Desktop\Francis Bautista\Images with Litter\bautista_y151.jpg</path>
	<source>
		<database>Unknown</database>
	</source>
	<size>
		<width>640</width>
		<height>640</height>
		<depth>3</depth>
	</size>
	<segmented>0</segmented>
	<object>
		<name>litter</name>
		<pose>Unspecified</pose>
		<truncated>0</truncated>
		<difficult>0</difficult>
		<bndbox>
			<xmin>621</xmin>
			<ymin>603</ymin>
			<xmax>633</xmax>
			<ymax>620</ymax>
		</bndbox>
	</object>
	<object>
		<name>litter</name>
		<pose>Unspecified</pose>
		<truncated>0</truncated>
		<difficult>0</difficult>
		<bndbox>
			<xmin>243</xmin>
			<ymin>625</ymin>
			<xmax>269</xmax>
			<ymax>638</ymax>
		</bndbox>
	</object>
	<object>
		<name>litter</name>
		<pose>Unspecified</pose>
		<truncated>0</truncated>
		<difficult>0</difficult>
		<bndbox>
			<xmin>70</xmin>
			<ymin>505</ymin>
			<xmax>89</xmax>
			<ymax>513</ymax>
		</bndbox>
	</object>
	<object>
		<name>litter</name>
		<pose>Unspecified</pose>
		<truncated>0</truncated>
		<difficult>0</difficult>
		<bndbox>
			<xmin>75</xmin>
			<ymin>456</ymin>
			<xmax>93</xmax>
			<ymax>465</ymax>
		</bndbox>
	</object>
</annotation>
