<annotation>
	<folder>Images with Litter</folder>
	<filename>Dominguez_y291.jpg</filename>
	<path>C:\Users\Gloria\Desktop\Dataset\Gloria Dominguez\Images with Litter\Dominguez_y291.jpg</path>
	<source>
		<database>Unknown</database>
	</source>
	<size>
		<width>640</width>
		<height>640</height>
		<depth>3</depth>
	</size>
	<segmented>0</segmented>
	<object>
		<name>litter</name>
		<pose>Unspecified</pose>
		<truncated>0</truncated>
		<difficult>0</difficult>
		<bndbox>
			<xmin>611</xmin>
			<ymin>456</ymin>
			<xmax>621</xmax>
			<ymax>467</ymax>
		</bndbox>
	</object>
	<object>
		<name>litter</name>
		<pose>Unspecified</pose>
		<truncated>0</truncated>
		<difficult>0</difficult>
		<bndbox>
			<xmin>403</xmin>
			<ymin>436</ymin>
			<xmax>407</xmax>
			<ymax>438</ymax>
		</bndbox>
	</object>
	<object>
		<name>litter</name>
		<pose>Unspecified</pose>
		<truncated>0</truncated>
		<difficult>0</difficult>
		<bndbox>
			<xmin>357</xmin>
			<ymin>507</ymin>
			<xmax>372</xmax>
			<ymax>517</ymax>
		</bndbox>
	</object>
	<object>
		<name>litter</name>
		<pose>Unspecified</pose>
		<truncated>0</truncated>
		<difficult>0</difficult>
		<bndbox>
			<xmin>240</xmin>
			<ymin>594</ymin>
			<xmax>253</xmax>
			<ymax>602</ymax>
		</bndbox>
	</object>
	<object>
		<name>litter</name>
		<pose>Unspecified</pose>
		<truncated>0</truncated>
		<difficult>0</difficult>
		<bndbox>
			<xmin>497</xmin>
			<ymin>419</ymin>
			<xmax>505</xmax>
			<ymax>427</ymax>
		</bndbox>
	</object>
	<object>
		<name>litter</name>
		<pose>Unspecified</pose>
		<truncated>0</truncated>
		<difficult>0</difficult>
		<bndbox>
			<xmin>386</xmin>
			<ymin>409</ymin>
			<xmax>394</xmax>
			<ymax>417</ymax>
		</bndbox>
	</object>
</annotation>
