<annotation>
	<folder>Images with litter</folder>
	<filename>johnson_y304.jpg</filename>
	<path>C:\Users\Emily\Desktop\Spring 2018\PSYC 333\Dataset\Images with litter\johnson_y304.jpg</path>
	<source>
		<database>Unknown</database>
	</source>
	<size>
		<width>640</width>
		<height>640</height>
		<depth>3</depth>
	</size>
	<segmented>0</segmented>
	<object>
		<name>litter</name>
		<pose>Unspecified</pose>
		<truncated>0</truncated>
		<difficult>0</difficult>
		<bndbox>
			<xmin>536</xmin>
			<ymin>519</ymin>
			<xmax>548</xmax>
			<ymax>527</ymax>
		</bndbox>
	</object>
	<object>
		<name>litter</name>
		<pose>Unspecified</pose>
		<truncated>0</truncated>
		<difficult>0</difficult>
		<bndbox>
			<xmin>429</xmin>
			<ymin>427</ymin>
			<xmax>434</xmax>
			<ymax>432</ymax>
		</bndbox>
	</object>
	<object>
		<name>litter</name>
		<pose>Unspecified</pose>
		<truncated>0</truncated>
		<difficult>0</difficult>
		<bndbox>
			<xmin>127</xmin>
			<ymin>575</ymin>
			<xmax>134</xmax>
			<ymax>583</ymax>
		</bndbox>
	</object>
	<object>
		<name>litter</name>
		<pose>Unspecified</pose>
		<truncated>0</truncated>
		<difficult>0</difficult>
		<bndbox>
			<xmin>598</xmin>
			<ymin>457</ymin>
			<xmax>601</xmax>
			<ymax>460</ymax>
		</bndbox>
	</object>
	<object>
		<name>litter</name>
		<pose>Unspecified</pose>
		<truncated>0</truncated>
		<difficult>0</difficult>
		<bndbox>
			<xmin>540</xmin>
			<ymin>432</ymin>
			<xmax>546</xmax>
			<ymax>437</ymax>
		</bndbox>
	</object>
	<object>
		<name>litter</name>
		<pose>Unspecified</pose>
		<truncated>0</truncated>
		<difficult>0</difficult>
		<bndbox>
			<xmin>481</xmin>
			<ymin>455</ymin>
			<xmax>483</xmax>
			<ymax>459</ymax>
		</bndbox>
	</object>
</annotation>
