<annotation>
	<folder>Images with litter</folder>
	<filename>stone_y63.jpg</filename>
	<path>C:\Users\Vivian Tang\Desktop\Amanda Stone\Images with litter\stone_y63.jpg</path>
	<source>
		<database>Unknown</database>
	</source>
	<size>
		<width>640</width>
		<height>640</height>
		<depth>3</depth>
	</size>
	<segmented>0</segmented>
	<object>
		<name>litter</name>
		<pose>Unspecified</pose>
		<truncated>0</truncated>
		<difficult>0</difficult>
		<bndbox>
			<xmin>348</xmin>
			<ymin>432</ymin>
			<xmax>357</xmax>
			<ymax>444</ymax>
		</bndbox>
	</object>
	<object>
		<name>litter</name>
		<pose>Unspecified</pose>
		<truncated>0</truncated>
		<difficult>0</difficult>
		<bndbox>
			<xmin>360</xmin>
			<ymin>405</ymin>
			<xmax>367</xmax>
			<ymax>417</ymax>
		</bndbox>
	</object>
	<object>
		<name>litter</name>
		<pose>Unspecified</pose>
		<truncated>0</truncated>
		<difficult>0</difficult>
		<bndbox>
			<xmin>471</xmin>
			<ymin>414</ymin>
			<xmax>477</xmax>
			<ymax>419</ymax>
		</bndbox>
	</object>
	<object>
		<name>litter</name>
		<pose>Unspecified</pose>
		<truncated>0</truncated>
		<difficult>0</difficult>
		<bndbox>
			<xmin>559</xmin>
			<ymin>454</ymin>
			<xmax>567</xmax>
			<ymax>461</ymax>
		</bndbox>
	</object>
</annotation>
